caplena/__init__.py
caplena/client.py
caplena/configuration.py
caplena/constants.py
caplena/errors.py
caplena/helpers.py
caplena/iterator.py
caplena/list.py
caplena/py.typed
caplena/version.py
caplena/api/__init__.py
caplena/api/api_base_uri.py
caplena/api/api_exception.py
caplena/api/api_filter.py
caplena/api/api_ordering.py
caplena/api/api_requestor.py
caplena/api/api_version.py
caplena/controllers/__init__.py
caplena/endpoints/__init__.py
caplena/endpoints/base_endpoint.py
caplena/endpoints/projects_endpoint.py
caplena/filters/__init__.py
caplena/filters/projects_filter.py
caplena/http/__init__.py
caplena/http/http_client.py
caplena/http/http_response.py
caplena/http/json_encoder.py
caplena/http/requests_http_client.py
caplena/logging/__init__.py
caplena/logging/default_logger.py
caplena/logging/logger.py
caplena/models/__init__.py
caplena/models/projects.py
caplena/resources/__init__.py
caplena/validations/__init__.py
caplena/validations/projects.py
caplena-2.1.2.dist-info/LICENSE
caplena-2.1.2.dist-info/WHEEL
caplena-2.1.2.dist-info/METADATA
caplena-2.1.2.dist-info/RECORD
