Metadata-Version: 2.1
Name: caplena
Version: 2.1.2
Summary: Python Library for Caplena REST API.
Keywords: caplena,api,nlp,customer feedback
Author-email: Caplena <support@caplena.com>
Maintainer-email: Pascal de Buren <pascal@caplena.com>
Requires-Python: >=3.8
Classifier: Development Status :: 4 - Beta
Classifier: License :: OSI Approved :: MIT License
Classifier: Typing :: Typed
Classifier: Intended Audience :: Developers
Classifier: Operating System :: OS Independent
Classifier: Topic :: Internet
Classifier: Topic :: Software Development :: Libraries :: Python Modules
Classifier: Topic :: Software Development :: Libraries
Classifier: Topic :: Software Development
Classifier: Programming Language :: Python
Classifier: Programming Language :: Python :: 3 :: Only
Classifier: Programming Language :: Python :: 3.8
Classifier: Programming Language :: Python :: 3.9
Classifier: Programming Language :: Python :: 3.10
Requires-Dist: requests >=2.26.0
Requires-Dist: typing-extensions >=4.0.0
Requires-Dist: backoff >=2.2.0
Requires-Dist: cachetools>=5.0.0
Requires-Dist: pydantic>=2.0.0
Requires-Dist: isort ; extra == "dev"
Requires-Dist: black ; extra == "dev"
Requires-Dist: flake8 ; extra == "dev"
Requires-Dist: pyright ; extra == "dev"
Requires-Dist: pre-commit ; extra == "dev"
Requires-Dist: mypy ; extra == "dev"
Requires-Dist: types-requests ; extra == "dev"
Requires-Dist: sphinx ; extra == "doc"
Requires-Dist: furo ; extra == "doc"
Requires-Dist: pytest ; extra == "test"
Requires-Dist: pytest-watch ; extra == "test"
Requires-Dist: requests-mock ; extra == "test"
Requires-Dist: types-cachetools ; extra == "test"
Requires-Dist: types-six ; extra == "test"
Requires-Dist: types-Pygments ; extra == "test"
Requires-Dist: types-colorama ; extra == "test"
Requires-Dist: types-setuptools ; extra == "test"
Project-URL: API Reference, https://caplena.com/docs/developers/
Project-URL: Bug Tracker, https://github.com/caplena/caplena-python/issues
Project-URL: Documentation, https://caplena.com/docs/sdk/python/
Project-URL: Homepage, https://caplena.com
Project-URL: Source Code, https://github.com/caplena/caplena-python
Provides-Extra: dev
Provides-Extra: doc
Provides-Extra: test
